snat/__init__.py
snat/__main__.py
snat/about.py
snat/achievement_list.py
snat/app.py
snat/game_list.py
snat/input_dialog.py
snat/settings.py
snat/steam_api.py
snat/utils.py
snat/asset/icon.ico
snat-0.3.0.dist-info/LICENSE
snat-0.3.0.dist-info/METADATA
snat-0.3.0.dist-info/WHEEL
snat-0.3.0.dist-info/entry_points.txt
snat-0.3.0.dist-info/top_level.txt
snat-0.3.0.dist-info/RECORD
